{
  "accuracy": 0.99638671875,
  "action_loss": 0.021188545296899973,
  "checkpoint_step": 123785,
  "checkpoint_updated_at": "2026-06-22T15:31:25Z",
  "continuous_action_loss": 0.0,
  "dataset_records": 0,
  "elapsed_hours": 0.015,
  "eta_hours": 1.425,
  "expected_steps": 1920,
  "global_step": 123785,
  "gpu_memory_total_mb": 15360.0,
  "gpu_memory_used_mb": 5201.0,
  "gpu_temperature_c": 60.0,
  "gpu_utilization_pct": 65.0,
  "local_step": 20,
  "log_dir": "20260712_140206_optimum_loopx_v1",
  "loss": 0.9526256050216034,
  "outcome_loss": 58.87171894098283,
  "progress_pct": 1.042,
  "reasoning_loss": 1.096827392000705,
  "remaining_steps": 1900,
  "reward_loss": 0.04282703276257962,
  "shard": 1,
  "source_updated_at": "2026-07-12T14:06:44Z",
  "state": "running",
  "tag_loss": 0.1566275620367378,
  "training_name": "20260712_140206_optimum_loopx_v1"
}
