{
  "accuracy": 0.9599087487348178,
  "action_loss": 0.2326242732523228,
  "checkpoint_step": 106970,
  "checkpoint_updated_at": "2026-06-21T08:40:34Z",
  "continuous_action_loss": 25.37176144241543,
  "dataset_records": 0,
  "elapsed_hours": 1.408,
  "eta_hours": 2.909,
  "expected_steps": 7574,
  "global_step": 106970,
  "gpu_memory_total_mb": 15360.0,
  "gpu_memory_used_mb": 5273.0,
  "gpu_temperature_c": 71.0,
  "gpu_utilization_pct": 67.0,
  "local_step": 2470,
  "log_dir": "agent_ua_20260621_072433_agent_ua",
  "loss": 11.428144300893809,
  "outcome_loss": 12.799582265163178,
  "progress_pct": 32.612,
  "reasoning_loss": 0.8943820707533916,
  "remaining_steps": 5104,
  "reward_loss": 0.12008518913828768,
  "shard": 1,
  "source_updated_at": "2026-06-21T08:56:36Z",
  "state": "running",
  "tag_loss": 0.3080093265914543,
  "training_name": "agent_ua_20260621_072433_agent_ua"
}
