{
  "accuracy": 0.9899101407158152,
  "action_loss": 0.033901058393252775,
  "checkpoint_step": 94465,
  "checkpoint_updated_at": "2026-06-19T00:56:26Z",
  "continuous_action_loss": 0.0,
  "dataset_records": 0,
  "elapsed_hours": 5.816,
  "eta_hours": 29.425,
  "expected_steps": 61896,
  "global_step": 94465,
  "gpu_memory_total_mb": 15360.0,
  "gpu_memory_used_mb": 4228.0,
  "gpu_temperature_c": 71.0,
  "gpu_utilization_pct": 71.0,
  "local_step": 10215,
  "log_dir": "general_machine_big_20260618_180316_general_machine_big_resume",
  "loss": 0.10793251012249956,
  "outcome_loss": 0.007974631789193963,
  "progress_pct": 16.503,
  "reasoning_loss": 0.22506556317023307,
  "remaining_steps": 51681,
  "reward_loss": 0.03720659061768353,
  "shard": 3,
  "source_updated_at": "2026-06-19T01:12:27Z",
  "state": "running",
  "tag_loss": 0.0,
  "training_name": "general_machine_big_20260618_180316_general_machine_big_resume"
}
