{
  "accuracy": 0.9902656838926479,
  "action_loss": 0.05465459914004333,
  "checkpoint_step": 115510,
  "checkpoint_updated_at": "2026-06-21T13:48:22Z",
  "continuous_action_loss": 3.8359447400523714,
  "dataset_records": 0,
  "elapsed_hours": 6.281,
  "eta_hours": 0.0,
  "expected_steps": 7574,
  "global_step": 115510,
  "gpu_memory_total_mb": 15360.0,
  "gpu_memory_used_mb": 5273.0,
  "gpu_temperature_c": 69.0,
  "gpu_utilization_pct": 56.0,
  "local_step": 11010,
  "log_dir": "agent_ua_20260621_072433_agent_ua",
  "loss": 2.4700239207032793,
  "outcome_loss": 3.7552356397108952,
  "progress_pct": 145.366,
  "reasoning_loss": 0.2798915811388525,
  "remaining_steps": 0,
  "reward_loss": 0.052270306715769474,
  "shard": 3,
  "source_updated_at": "2026-06-21T13:48:54Z",
  "state": "running",
  "tag_loss": 0.1761872482679219,
  "training_name": "agent_ua_20260621_072433_agent_ua"
}
