{
  "accuracy": 0.9909995765705384,
  "action_loss": 0.029103048067761542,
  "checkpoint_step": 98050,
  "checkpoint_updated_at": "2026-06-19T03:13:15Z",
  "continuous_action_loss": 0.0,
  "dataset_records": 0,
  "elapsed_hours": 7.862,
  "eta_hours": 27.401,
  "expected_steps": 61896,
  "global_step": 98050,
  "gpu_memory_total_mb": 15360.0,
  "gpu_memory_used_mb": 4228.0,
  "gpu_temperature_c": 71.0,
  "gpu_utilization_pct": 56.0,
  "local_step": 13800,
  "log_dir": "general_machine_big_20260618_180316_general_machine_big_resume",
  "loss": 0.08821853583807124,
  "outcome_loss": 0.006550499731161377,
  "progress_pct": 22.295,
  "reasoning_loss": 0.1792671966655665,
  "remaining_steps": 48096,
  "reward_loss": 0.03042651798245677,
  "shard": 4,
  "source_updated_at": "2026-06-19T03:15:14Z",
  "state": "running",
  "tag_loss": 0.0,
  "training_name": "general_machine_big_20260618_180316_general_machine_big_resume"
}
